LICENSE
MANIFEST.in
README.md
setup.cfg
setup.py
csrc/kernels.cpp
csrc/vertical_slash_index.cu
minference/__init__.py
minference/minference_configuration.py
minference/models_patch.py
minference/patch.py
minference/utils.py
minference/version.py
minference.egg-info/PKG-INFO
minference.egg-info/SOURCES.txt
minference.egg-info/dependency_links.txt
minference.egg-info/not-zip-safe
minference.egg-info/requires.txt
minference.egg-info/top_level.txt
minference/configs/GLM_4_9B_1M_instruct_kv_out_v32_fit_o_best_pattern.json
minference/configs/Llama_3.1_70B_Instruct_128k_kv_out_v32_fit_o_best_pattern_v2.json
minference/configs/Llama_3.1_8B_Instruct_128k_kv_out_v32_fit_o_best_pattern.json
minference/configs/Llama_3.1_8B_Instruct_128k_kv_out_v32_fit_o_best_pattern_v2.json
minference/configs/Llama_3_70B_Instruct_262k_kv_out_v32_fit_o_best_pattern.json
minference/configs/Llama_3_8B_Instruct_262k_kv_out_v32_fit_o_best_pattern.json
minference/configs/Phi_3_mini_128k_instruct_kv_out_v32_fit_o_best_pattern.json
minference/configs/Qwen2.5_14B_Instruct_1M.json
minference/configs/Qwen2.5_32B_Instruct_128k_kv_out_v32_fit_o_best_pattern.json
minference/configs/Qwen2.5_72B_Instruct_128k_kv_out_v32_fit_o_best_pattern.json
minference/configs/Qwen2.5_7B_Instruct_128k_instruct_kv_out_v32_fit_o_best_pattern.json
minference/configs/Qwen2.5_7B_Instruct_1M.json
minference/configs/Qwen2_7B_Instruct_128k_instruct_kv_out_v32_fit_o_best_pattern.json
minference/configs/Yi_9B_200k_kv_out_v32_fit_o_best_pattern.json
minference/configs/__init__.py
minference/configs/model2path.py
minference/modules/__init__.py
minference/modules/flexprefill.py
minference/modules/forward.py
minference/modules/inf_llm.py
minference/modules/kivi.py
minference/modules/kvcompression.py
minference/modules/minference_forward.py
minference/modules/pyramidkv.py
minference/modules/quest.py
minference/modules/retr_attn.py
minference/modules/snapkv.py
minference/modules/xattention.py
minference/ops/__init__.py
minference/ops/block_sparse_flash_attention.py
minference/ops/flash_attn_triton.py
minference/ops/pit_sparse_flash_attention.py
minference/ops/pit_sparse_flash_attention_v2.py
minference/ops/streaming_kernel.py
