Metadata-Version: 2.2
Name: minference
Version: 0.1.6.0
Summary: To speed up Long-context LLMs' inference, approximate and dynamic sparse calculate the attention, which reduces inference latency by up to 10x for pre-filling on an A100 while maintaining accuracy.
Home-page: https://github.com/microsoft/MInference
Author: The MInference team
Author-email: hjiang@microsoft.com
License: MIT License
Keywords: LLMs Inference,Long-Context LLMs,Dynamic Sparse Attention,Efficient Inference
Classifier: Intended Audience :: Science/Research
Classifier: Development Status :: 3 - Alpha
Classifier: Programming Language :: Python :: 3
Classifier: Topic :: Scientific/Engineering :: Artificial Intelligence
Requires-Python: >=3.8.0
License-File: LICENSE
Requires-Dist: transformers>=4.37.0
Requires-Dist: torch
Requires-Dist: triton
Requires-Dist: einops
Provides-Extra: dev
Requires-Dist: transformers>=4.37.0; extra == "dev"
Requires-Dist: torch; extra == "dev"
Requires-Dist: triton; extra == "dev"
Requires-Dist: einops; extra == "dev"
Requires-Dist: black==21.4b0; extra == "dev"
Requires-Dist: flake8>=3.8.3; extra == "dev"
Requires-Dist: isort>=5.5.4; extra == "dev"
Requires-Dist: pre-commit; extra == "dev"
Requires-Dist: pytest; extra == "dev"
Requires-Dist: pytest-xdist; extra == "dev"
Provides-Extra: quality
Requires-Dist: black==21.4b0; extra == "quality"
Requires-Dist: flake8>=3.8.3; extra == "quality"
Requires-Dist: isort>=5.5.4; extra == "quality"
Requires-Dist: pre-commit; extra == "quality"
Requires-Dist: pytest; extra == "quality"
Requires-Dist: pytest-xdist; extra == "quality"
Dynamic: author
Dynamic: author-email
Dynamic: classifier
Dynamic: description
Dynamic: description-content-type
Dynamic: home-page
Dynamic: keywords
Dynamic: license
Dynamic: provides-extra
Dynamic: requires-dist
Dynamic: requires-python
Dynamic: summary
